{
  "products": [
    {
      "id": 1,
      "name": "Fresh Apples",
      "price": 120,
      "originalPrice": 150,
      "discount": 20,
      "category": "Fruits",
      "image": "🍎",
      "rating": 4.5,
      "reviews": 234,
      "unit": "kg",
      "inStock": true
    },
    {
      "id": 2,
      "name": "Bananas",
      "price": 50,
      "originalPrice": null,
      "discount": null,
      "category": "Fruits",
      "image": "🍌",
      "rating": 4.7,
      "reviews": 189,
      "unit": "dozen",
      "inStock": true
    },
    {
      "id": 3,
      "name": "Fresh Tomatoes",
      "price": 40,
      "originalPrice": 60,
      "discount": 33,
      "category": "Vegetables",
      "image": "🍅",
      "rating": 4.3,
      "reviews": 156,
      "unit": "kg",
      "inStock": true
    },
    {
      "id": 4,
      "name": "Potatoes",
      "price": 30,
      "originalPrice": null,
      "discount": null,
      "category": "Vegetables",
      "image": "🥔",
      "rating": 4.6,
      "reviews": 298,
      "unit": "kg",
      "inStock": true
    },
    {
      "id": 5,
      "name": "Fresh Milk",
      "price": 60,
      "originalPrice": null,
      "discount": null,
      "category": "Dairy",
      "image": "🥛",
      "rating": 4.8,
      "reviews": 412,
      "unit": "liter",
      "inStock": true
    },
    {
      "id": 6,
      "name": "Cheese Block",
      "price": 200,
      "originalPrice": null,
      "discount": null,
      "category": "Dairy",
      "image": "🧀",
      "rating": 4.4,
      "reviews": 178,
      "unit": "250g",
      "inStock": false
    },
    {
      "id": 7,
      "name": "Fresh Bread",
      "price": 40,
      "originalPrice": null,
      "discount": null,
      "category": "Bakery",
      "image": "🍞",
      "rating": 4.5,
      "reviews": 267,
      "unit": "loaf",
      "inStock": true
    },
    {
      "id": 8,
      "name": "Butter Croissant",
      "price": 80,
      "originalPrice": 100,
      "discount": 20,
      "category": "Bakery",
      "image": "🥐",
      "rating": 4.6,
      "reviews": 145,
      "unit": "pack",
      "inStock": true
    },
    {
      "id": 9,
      "name": "Potato Chips",
      "price": 50,
      "originalPrice": null,
      "discount": null,
      "category": "Snacks",
      "image": "🍿",
      "rating": 4.2,
      "reviews": 321,
      "unit": "pack",
      "inStock": true
    },
    {
      "id": 10,
      "name": "Chocolate Cookies",
      "price": 90,
      "originalPrice": null,
      "discount": null,
      "category": "Snacks",
      "image": "🍪",
      "rating": 4.7,
      "reviews": 289,
      "unit": "pack",
      "inStock": true
    },
    {
      "id": 11,
      "name": "Fresh Oranges",
      "price": 100,
      "originalPrice": null,
      "discount": null,
      "category": "Fruits",
      "image": "🍊",
      "rating": 4.4,
      "reviews": 198,
      "unit": "kg",
      "inStock": true
    },
    {
      "id": 12,
      "name": "Baby Carrots",
      "price": 35,
      "originalPrice": null,
      "discount": null,
      "category": "Vegetables",
      "image": "🥕",
      "rating": 4.5,
      "reviews": 234,
      "unit": "kg",
      "inStock": true
    },
    {
      "id": 13,
      "name": "Grapes",
      "price": 150,
      "originalPrice": 180,
      "discount": 17,
      "category": "Fruits",
      "image": "🍇",
      "rating": 4.6,
      "reviews": 167,
      "unit": "kg",
      "inStock": true
    },
    {
      "id": 14,
      "name": "Broccoli",
      "price": 80,
      "originalPrice": null,
      "discount": null,
      "category": "Vegetables",
      "image": "🥦",
      "rating": 4.3,
      "reviews": 143,
      "unit": "kg",
      "inStock": true
    },
    {
      "id": 15,
      "name": "Yogurt",
      "price": 45,
      "originalPrice": null,
      "discount": null,
      "category": "Dairy",
      "image": "🥣",
      "rating": 4.7,
      "reviews": 312,
      "unit": "500ml",
      "inStock": true
    },
    {
      "id": 16,
      "name": "Cupcakes",
      "price": 120,
      "originalPrice": 150,
      "discount": 20,
      "category": "Bakery",
      "image": "🧁",
      "rating": 4.8,
      "reviews": 278,
      "unit": "pack",
      "inStock": true
    },
    {
        "id": 17,
        "name": "Curd",
        "price": 50,
        "originalPrice": null,
        "discount": 10,
        "category": "Dairy",
        "image": "🍶",
        "rating": 4.6,
        "reviews": 234,
        "unit": "500g",
        "inStock": true
    },
    {
        "id": 18,
        "name": "Butter",
        "price": 120,
        "originalPrice": 150,
        "discount": 20,
        "category": "Dairy",
        "image": "🧈",
        "rating": 4.9,
        "reviews": 310,
        "unit": "200g",
        "inStock": true
    },
    {
        "id": 19,
        "name": "Blueberry Muffin",
        "price": 70,
        "originalPrice": 90,
        "discount": 22,
        "category": "Bakery",
        "image": "🫐",
        "rating": 4.7,
        "reviews": 134,
        "unit": "piece",
        "inStock": true
    },
    {
        "id": 20,
        "name": "Cinnamon Roll",
        "price": 55,
        "originalPrice": null,
        "discount": null,
        "category": "Bakery",
        "image": "🍥",
        "rating": 4.6,
        "reviews": 160,
        "unit": "piece",
        "inStock": true
    },
    {
    "id": 21,
    "name": "Banana Bread",
    "price": 90,
    "originalPrice": 110,
    "discount": 18,
    "category": "Bakery",
    "image": "🍌",
    "rating": 4.8,
    "reviews": 120,
    "unit": "loaf",
    "inStock": true
    },
    {
    "id": 22,
    "name": "Chocolate Eclair",
    "price": 85,
    "originalPrice": 100,
    "discount": 15,
    "category": "Bakery",
    "image": "🍫",
    "rating": 4.7,
    "reviews": 98,
    "unit": "piece",
    "inStock": true
    },
    {
    "id": 23,
    "name": "Apple Pie Slice",
    "price": 60,
    "originalPrice": 75,
    "discount": 20,
    "category": "Bakery",
    "image": "🥧",
    "rating": 4.5,
    "reviews": 142,
    "unit": "slice",
    "inStock": true
    },
    {
  "id": 24,
  "name": "Salted Peanuts",
  "price": 40,
  "originalPrice": null,
  "discount": null,
  "category": "Snacks",
  "image": "🥜",
  "rating": 4.3,
  "reviews": 210,
  "unit": "pack",
  "inStock": true
},
{
  "id": 25,
  "name": "Corn Flakes Snack",
  "price": 35,
  "originalPrice": 50,
  "discount": 30,
  "category": "Snacks",
  "image": "🌽",
  "rating": 4.1,
  "reviews": 150,
  "unit": "pack",
  "inStock": true
},
{
  "id": 26,
  "name": "Cheese Balls",
  "price": 60,
  "originalPrice": 75,
  "discount": 20,
  "category": "Snacks",
  "image": "🧀",
  "rating": 4.5,
  "reviews": 180,
  "unit": "pack",
  "inStock": true
}


  ]
}